setup.py
s1231/_init_.py
s1231.egg-info/PKG-INFO
s1231.egg-info/SOURCES.txt
s1231.egg-info/dependency_links.txt
s1231.egg-info/not-zip-safe
s1231.egg-info/top_level.txt