Metadata-Version: 1.0
Name: s1231
Version: 0.1
Summary: sample
Home-page: https://gist.github.com/Rajeev69/d52bf134280efba403d5
Author: Rajeev69
Author-email: rajeev.r@roanuz.com
License: LICENSE.txt
Platform: UNKNOWN
